{
    "term": "reasoner",
    "part-of-speech": "ainmfhocal",
    "citation-form": "córas réasúnaíochta",
    "def-en": "In the context of machine learning, the use of logical rules to predict new facts.",
    "def-ga": "I gcomhthéacs ríomhfhoghlama, úsáid rialacha loighce chun fíricí nua a réamhinsint..",

    "prov": {
        "réasúnaíocht": "de-bhaldraithe, focloir-beag, odonaill"
    },
    "notes": [
        "Cé go bhfuil 'réasúnaí' i bhFoclóir De Bhaldraithe mar 'reasoner' is i gcomhthéacs daoine amháin atá an téarma seo. Thairis sin, tá an téarma sin luaite mar leagan den téarma Béarla 'rationalist' i bhFoclóir De Bhaldraithe agus i bhFoclóir Uí Dhónaill -- sainmhíniú nach luíonn leis an úsáid atá de dhíth anseo. Ní ghlactar le 'réasúnaí' mar sin.",
        "Toisc gur córas ríomhaireachta a bhíonn i gceist i gcónaí le 'reasoner', meastar go bhfuil 'córas réasúnaíochta' soiléir mar théarma. Thairis sin, cloíonn sé le téarmaí eile sa bhFoclóir seo (atá bunaithe chomh maith ar an bhfocal réasúnaíocht).",
        "Féach chomh maith ar an téarma 'reasoning / réasúnaíocht'."
    ]
}